mailables/__init__.py
mailables/config.py
mailables/exceptions.py
mailables/importer.py
mailables/mailer.py
mailables/message.py
mailables/transports.py
mailables-0.0.2.dist-info/LICENSE
mailables-0.0.2.dist-info/WHEEL
mailables-0.0.2.dist-info/METADATA
mailables-0.0.2.dist-info/RECORD
