Metadata-Version: 2.1
Name: mailables
Version: 0.0.2
Summary: A developer-centric utility for sending asynchronous mails.
Home-page: https://github.com/alex-oleshkevich/mailables
Keywords: asyncio,email,mailer,mail
Author: Alex Oleshkevich
Author-email: alex.oleshkevich@gmail.com
Requires-Python: >=3.7,<4.0
Classifier: Programming Language :: Python :: 3
Classifier: Programming Language :: Python :: 3.7
Classifier: Topic :: Software Development :: Libraries :: Python Modules
Provides-Extra: aiofiles
Provides-Extra: aiosmtplib
Provides-Extra: full
Requires-Dist: aiofiles (>=0.4.0,<0.5.0); extra == "aiofiles" or extra == "full"
Requires-Dist: aiosmtplib (>=1.1,<2.0); extra == "aiosmtplib" or extra == "full"
Project-URL: Repository, https://github.com/alex-oleshkevich/mailables.git
